appstore/__init__.py
appstore-0.0.4.dist-info/LICENSE
appstore-0.0.4.dist-info/METADATA
appstore-0.0.4.dist-info/WHEEL
appstore-0.0.4.dist-info/top_level.txt
appstore-0.0.4.dist-info/RECORD
